neutron_tavi-0.1.1.dist-info/licenses/LICENSE
tavi/__init__.py
tavi/_version.py
tavi/configuration.py
tavi/configuration_template.ini
tavi/convert_spice_to_nexus.py
tavi/lattice_algorithm.py
tavi/plotter.py
tavi/sample.py
tavi/ub_algorithm.py
tavi/utilities.py
tavi/version.py
tavi/data/convfit.py
tavi/data/fit.py
tavi/data/nexus_builder.py
tavi/data/nexus_entry.py
tavi/data/scan.py
tavi/data/scan_data.py
tavi/data/scan_group.py
tavi/data/spice_reader.py
tavi/data/tavi.py
tavi/instrument/tas.py
tavi/instrument/tas_base.py
tavi/instrument/components/collimators.py
tavi/instrument/components/component_base.py
tavi/instrument/components/detector.py
tavi/instrument/components/goni.py
tavi/instrument/components/guide.py
tavi/instrument/components/monitor.py
tavi/instrument/components/mono_ana.py
tavi/instrument/components/source.py
tavi/instrument/resolution/convolution.py
tavi/instrument/resolution/cooper_nathans.py
tavi/instrument/resolution/curve.py
tavi/instrument/resolution/ellipse.py
tavi/instrument/resolution/ellipsoid.py
tavi/instrument/resolution/resolution_calculator.py
neutron_tavi-0.1.1.dist-info/METADATA
neutron_tavi-0.1.1.dist-info/WHEEL
neutron_tavi-0.1.1.dist-info/top_level.txt
neutron_tavi-0.1.1.dist-info/RECORD
