Metadata-Version: 2.4
Name: neutron_tavi
Version: 0.1.1
Summary: Triple-Axis Data Visualization Toolkit
Author-email: Bing Li <lib1@ornl.gov>
License-Expression: LGPL-3.0-or-later
Project-URL: homepage, https://github.com/neutrons/TAVI
Requires-Python: >=3.10
License-File: LICENSE
Dynamic: license-file
